nttl/__init__.py
nttl/data.py
nttl/dt.py
nttl/main.py
nttl/report.py
nttl/version.py
nttl-0.4.0.dist-info/LICENSE
nttl-0.4.0.dist-info/METADATA
nttl-0.4.0.dist-info/WHEEL
nttl-0.4.0.dist-info/entry_points.txt
nttl-0.4.0.dist-info/top_level.txt
nttl-0.4.0.dist-info/RECORD
