Metadata-Version: 2.1
Name: nttl
Version: 0.4.0
Summary: Tiny time tracker for the commandline
Author-email: R <contact+nttl@vonshednob.cc>
License: GPLv3
Project-URL: website, https://vonshednob.cc/nttl
Project-URL: repository, https://codeberg.org/vonshednob/pter
Requires-Python: >=3.11
License-File: LICENSE
Provides-Extra: xdg
Requires-Dist: pyxdg; extra == "xdg"
